<?xml version="1.0" encoding="UTF-8"?>
<livraria>
    <livro>
        <id>1</id>
        <titulo>One Piece</titulo>
        <autor>Eiichiro Oda</autor>
        <genero>Aventura</genero>
        <preco>39.90</preco>
        <status>Disponível</status>
    </livro>
    <livro>
        <id>2</id>
        <titulo>Harry Potter e a Pedra Filosofal</titulo>
        <autor>J.K. Rowling</autor>
        <genero>Fantasia</genero>
        <preco>49.90</preco>
        <status>Disponível</status>
    </livro>
    <livro>
        <id>3</id>
        <titulo>O Senhor dos Anéis: A Sociedade do Anel</titulo>
        <autor>J.R.R. Tolkien</autor>
        <genero>Fantasia</genero>
        <preco>59.90</preco>
        <status>Indisponível</status>
    </livro>
    <livro>
        <id>4</id>
        <titulo>Código Da Vinci</titulo>
        <autor>Dan Brown</autor>
        <genero>Suspense</genero>
        <preco>29.90</preco>
        <status>Disponível</status>
    </livro>
    <livro>
        <id>5</id>
        <titulo>1984</titulo>
        <autor>George Orwell</autor>
        <genero>Ficção Científica</gener
          
